torchcheck/__init__.py
torchcheck/checks.py
torchcheck/py.typed
torchcheck/return_types.py
torchcheck/torchcheck.py
torchcheck/ops/__init__.py
torchcheck/ops/expand.py
torchcheck/ops/inclusive_cumsum.py
torchcheck/ops/unsqueeze.py
torchcheck-1.0.8.dist-info/METADATA
torchcheck-1.0.8.dist-info/WHEEL
torchcheck-1.0.8.dist-info/top_level.txt
torchcheck-1.0.8.dist-info/RECORD
