Metadata-Version: 2.2
Name: torchcheck
Version: 1.0.8
Summary: Helper functions for pytorch, expand and unsqueeze with strings, inclusive cumsum
Author-email: Moritz Hennen <mail@fleonce.de>
Maintainer-email: Moritz Hennen <mail@fleonce.de>
Requires-Python: >=3.10
